lazygitgpt/__init__.py
lazygitgpt/__main__.py
lazygitgpt/cli.py
lazygitgpt/agents/__init__.py
lazygitgpt/agents/cli_agent.py
lazygitgpt/datasources/__init__.py
lazygitgpt/datasources/repos.py
lazygitgpt/git/__init__.py
lazygitgpt/git/operations.py
lazygitgpt/llms/__init__.py
lazygitgpt/llms/openai.py
lazygitgpt/memory/__init__.py
lazygitgpt/memory/memory.py
lazygitgpt/parsers/__init__.py
lazygitgpt/prompts/__init__.py
lazygitgpt/retrievers/__init__.py
lazygitgpt/retrievers/retrievalqa.py
lazygitgpt/utils/__init__.py
lazygitgpt-0.1.1.dist-info/LICENSE
lazygitgpt-0.1.1.dist-info/METADATA
lazygitgpt-0.1.1.dist-info/WHEEL
lazygitgpt-0.1.1.dist-info/entry_points.txt
lazygitgpt-0.1.1.dist-info/top_level.txt
lazygitgpt-0.1.1.dist-info/RECORD
