Metadata-Version: 2.1
Name: lazygitgpt
Version: 0.1.1
Summary: A tool to manage git repositories using GPT-4.
Home-page: https://github.com/shankarpandala/lazygitgpt
Author: Shankar Pandala
Author-email: shankar@ssbm.ch
Project-URL: Bug Tracker, https://github.com/shankarpandala/lazygitgpt/issues
Classifier: Programming Language :: Python :: 3
Classifier: License :: OSI Approved :: MIT License
Classifier: Operating System :: OS Independent
Requires-Python: >=3.9
License-File: LICENSE
Requires-Dist: gitpython >=3.1.0
Requires-Dist: openai >=0.10.0
